{
  "ID": "55667",
  "用户": "尹先凤",
  "活动": "第十四届幼儿教师优秀论文征集活动",
  "类型名称": "论文",
  "标题": "大班幼儿频繁告状行为的发展机制与教育干预研究",
  "作者": "尹先凤",
  "单位名称": "大连长兴岛经济技术开发区凤鸣幼儿园",
  "省市": "辽宁省大连市",
  "内容": "摘要 ： 本研究以幼儿园大班（5-6岁）幼儿为对象，通过为期12周的自然观察与案例追踪，发现幼儿告状行为发生率达3.2次/小时，涉及物品冲突（41%）、规则维护（35%）、情感表达（24%）三大类。研究结合皮亚杰道德发展理论、埃里克森自我同一性理论及社会学习理论，揭示告状行为本质是幼儿道德认知冲突、自我意识觉醒、社交策略局限的综合表现。通过“认知重构-能力建构-环境重塑”三维干预策略，使告状频率降低63%，自主解决冲突能力提升47%。研究为理解幼儿社会性行为发展提供实证依据，为幼儿园班级管理提供可操作的实践方案。关键词 ： 幼儿告状行为；道德发展；自我意识；社交能力；教育干预正文 ：一、问题的提出：被打断的教学节奏2024年9月的某周一上午，阳光幼儿园大一班的建构区正上演着“积木争夺战”。8:15-8:30的15分钟内的餐后游戏环节，教师连续收到5起告状：绍锋指控鹏飞“抢红色长积木”，馨慧哭诉俊熙“故意推倒城堡”，鹏飞举报圣捷“用了我的三角形屋顶”......这些此起彼伏的告状声如同教学活动的“不和谐音符”，不仅打断了教师的指导节奏，更引发研究者的思考：为何5岁幼儿如此依赖“告状”解决问题？这种行为背后隐藏着怎样的发展密码？根据教育部《3-6岁儿童学习与发展指南》，5-6岁幼儿应“能按自己的想法进行游戏或其他活动”“与同伴发生冲突时能自己协商解决”。然而实地观察发现，大班幼儿告状频率高达3.2次/小时（N=120课时），显著高于中班的1.8次/小时（p<0.05）。这些告状不仅发生在自由游戏（占比58%），更延伸至集体教学（22%）、生活环节（20%），涉及物品归属、规则遵守、情感伤害等多维度冲突。这种现象与国内外研究形成呼应。美国儿童心理学家Dodge指出，幼儿告状本质是“社会信息加工能力不足”的表现；国内学者王振宇发现，6岁前幼儿告状行为呈现“规则敏感期”的典型特征。但现有研究多停留于现象描述，缺乏对具体情境的深度解析与干预策略的实证研究。本研究试图通过微观叙事，揭示告状行为的发展机制，并探索有效的教育转化路径。二、田野记录：告状背后的成长密码（一）场景一：建构区的“正义捍卫者”（2024.9.189:05）“老师！他拿了我的彩虹桥！”朵朵举着半块蓝色积木，眼泪在眼眶里打转。被指控的毛衣慌忙辩解：“这是公共积木，我先看到的！”两人僵持时，一旁的乐乐突然插话：“老师，昨天朵朵也抢过我的轮子！”这场由积木引发的冲突，迅速演变为“旧账清算”。教师观察记录显示：85%的物品类告状涉及“所有权模糊”的材料（如公共积木、未标记的蜡笔），幼儿对“我的”“他的”“大家的”物权认知正处于建构期。（二）场景二：课堂上的“规则警察”（2024.9.209:45）科学活动《沉浮小实验》中，当老师示范完毕，浩浩突然举手：“老师，圣捷没举手就说话！”正在分享的圣捷涨红了脸，小声嘀咕：“我只是想问...”类似的“规则告状”占比35%，幼儿常以“老师说过...”作为指控依据。皮亚杰的道德认知理论在此得到印证——5-6岁幼儿处于“他律道德阶段”，将规则视为绝对权威，对“违规”行为的零容忍折射出道德认知的刻板性。（三）场景三：洗手间的“情感侦探”（2024.9.22 11:00）午餐前的盥洗环节，馨慧突然跑向老师：“晴晴不让我插队！”被冤枉的晴晴急得跺脚：“她昨天也不让我排！”这场看似无理的告状，实则是幼儿情感需求的表达——馨慧因感冒缺席两天，渴望通过“插队”重新获得同伴关注。研究发现，24%的告状隐含情感诉求，幼儿尚未掌握“我需要...”的直接表达，转而借助“告状”寻求情感联结。这些鲜活的案例揭示：幼儿告状绝非简单的“打小报告”，而是道德认知、自我意识、社交能力交织发展的外显行为。正如维果茨基所言，“告状是幼儿在最近发展区内寻求成人帮助的社会性行为”，既是成长的烦恼，也是教育的契机。三、原因剖析：三维度的发展解析（一）道德认知的“绝对化”困境（认知维度）根据科尔伯格道德发展阶段理论，大班幼儿处于“惩罚与服从定向阶段”向“人际服从定向阶段”过渡期。他们能识别明显的违规行为（如抢玩具），但缺乏情境化理解能力。在200例告状案例中，68%的幼儿坚持“他就是错了”，拒绝接受“不小心”“想一起玩”等解释。这种道德判断的绝对性，源于前额叶皮层尚未成熟，难以进行复杂的心理归因。典型案例：当老师问绍锋“鹏飞为什么拿你的积木”，他坚定回答：“因为他就想抢我的！”即使目睹鹏飞用该积木加固倒塌的桥梁，仍坚持最初判断。这种“结果导向”的道德评价，反映出幼儿道德认知的具象化特征。（二）自我意识的“膨胀与脆弱”（心理维度）埃里克森的发展阶段理论指出，5-6岁幼儿处于“主动感vs内疚感”的关键期。自我意识的觉醒使他们高度关注自身权益，却尚未建立同理能力。观察发现，告状幼儿在描述冲突时，73%使用“我”“我的”开头（如“我先拿到的”“他弄坏我的”），仅12%提及对方感受。这种“自我中心”的表达方式，本质是自我保护与寻求认同的双重需求——既希望维护权益，又渴望通过“正确告状”获得教师关注。数据佐证：在“为什么告状”的访谈中，41%幼儿回答“老师会帮我”，35%说“我要告诉老师我是对的”，仅24%提及“不想让他继续错”。这揭示告状行为的核心动机：寻求权威支持＞维护公平正义。（三）社交策略的“技能缺失”（行为维度）社会学习理论表明，幼儿的冲突解决策略主要通过观察模仿获得。然而，62%的家长报告“孩子在家告状会得到立即回应”，78%的教师承认“曾因省事直接介入冲突”。这种“替代解决”导致幼儿缺失关键经验——当被问及“如果老师不在怎么办”，83%幼儿表示“不知道”或“继续哭”。能力短板分析：冲突类型幼儿常用策略有效策略缺失物品争夺直接抢夺/告状协商交换、轮流玩规则冲突机械复述规则情境化解释、灵活调整情感冲突攻击/退缩情感表达、主动修复这种“社交技能赤字”在角色扮演实验中尤为明显：当模拟“同伴拒绝分享”场景时，仅有17%幼儿尝试说“我们轮流玩好吗”，68%选择直接告状或放弃。四、教育干预：三维度的支持体系（一）认知重构：搭建“道德思考阶梯”（每周2次，持续8周）1. 故事解构法：改编《三只小猪》为《积木保卫战》，引导幼儿讨论“大灰狼真的坏吗？”“有没有其他解决办法？”通过两难问题（如“拿错积木要不要道歉”），促进道德推理从“绝对化”向“情境化”转变。2. 情感温度计：设计情绪卡片（开心、生气、委屈、害怕），在告状时引导幼儿先贴卡片再描述：“你现在是哪种颜色？鹏飞拿积木时是什么颜色？”帮助建立双重视角。3. 规则小议会：每月召开“班级法庭”，让幼儿投票制定《建构区公约》，通过角色扮演审判“抢积木案”，理解规则的灵活性（如“紧急加固可以借用，但需说谢谢”）。实施成效：干预后，幼儿道德判断中“考虑动机”的比例从21%提升至58%，能说出“他可能没看见”的幼儿增加3倍。（二）能力建构：创设“冲突解决工作坊”（每日渗透，持续12周）1. 三步沟通法：教授“描述事实+表达感受+提出请求”的公式，如“你拿了我的红积木（事实），我很着急（感受），可以还给我吗？（请求）”。通过木偶剧、情景模拟反复练习，累计开展48次小组演练。2. 问题解决树：在教室设置“怎么办”互动墙，张贴常见冲突场景（如“他不让我玩”“作品被碰倒”），提供“问问他为什么”“一起修”“找老师”等选项，鼓励幼儿自主选择。3. 正向强化机制：设立“和平小卫士”勋章，每周表彰3名自主解决冲突的幼儿。数据显示，勋章激励使主动协商行为增加47%，告状时说“我们自己解决”的比例从9%升至38%。（三）环境重塑：建立“支持性回应”体系（教师行为调整）1. 延迟回应策略：制定“三问原则”——“发生了什么？””你觉得为什么会这样？”“你想怎么解决？”将介入时机从“即时处理”调整为“先倾听，后引导”。观察记录显示，教师平均介入时间从28秒延长至1分15秒，幼儿自主思考时间显著增加。2. 减少权威依赖：当幼儿告状时，教师改用“你们觉得呢？”引发同伴讨论。在建构区试点“调解员”制度，由幼儿轮流担任，负责记录冲突、组织协商，教师仅担任“顾问”。3. 家园协同共育：通过《家庭冲突解决指南》，指导家长在家中采用“同理-提问-鼓励”三步法：“你看起来很难过（同理），发生了什么？（提问）你觉得可以怎么做？（鼓励）”。跟踪调查显示，家庭干预组幼儿在园告状频率比对照组低29%。五、效果评估：从“告状专业户”到“和平小使者”（一）量化数据对比（N=28名幼儿）指标干预前干预后变化率告状频率（次/小时）3.21.2↓63%自主解决率17%64%↑47%同伴协商成功率29%71%↑42%教师介入时间（秒）2875↑168%（二）质性转变案例案例1：绍锋的“积木外交”干预前：每次冲突必告状，常说“他抢我的”。干预后：某日看见毛衣拿走最后一块长积木，主动说：“我们的城堡需要这个当桥，你用完可以借给我吗？”毛衣同意后，两人合作搭建了“双层立交桥”。教师记录：这是绍锋第1次自主协商成功。案例2：班级的“道歉日”5月的某周一，馨慧主动走到晴晴面前：“上次我不该说你坏话，对不起。”晴晴愣了一下，掏出一颗贴纸：“送你，我们和好吧！”这是班级首次出现自发的道歉行为，标志着幼儿从“依赖告状”转向“主动修复”。（三）教师反思老师记录：“过去总觉得告状是麻烦，现在发现每一次告状都是教育契机。当孩子们开始说'我们自己试试'，我知道他们正在长出解决问题的翅膀。”这种转变印证了维果茨基的“最近发展区”理论——教师的适度退后，正是幼儿向前成长的动力。六、结论与展望本研究揭示，幼儿告状行为是道德认知、自我意识、社交能力发展的“混合信号”，既需理解其发展合理性，更需提供阶梯式支持。通过认知重构、能力建构、环境重塑的三维干预，不仅降低了告状频率，更重要的是培养了幼儿的社会情感能力，为幼小衔接奠定坚实基础。参考文献 ： [1] 王振宇. 幼儿告状行为的发展心理学分析[J]. 学前教育研究,2018(05):35-42.  \n[2] Dodge K A. Social Cognition and Children's Aggressive Behavior[J]. Child Development,1993,64(5):1628-1638.  \n[3] 教育部. 3-6岁儿童学习与发展指南[Z]. 2012.  \n[4] 维果茨基. 思维与语言[M]. 李维译. 北京大学出版社,2010:123-128.  \n[5] Wellman H M. Making Minds: How Theory of Mind Develops[M]. Oxford University Press,2014:78-92.  \n[6] 李红, 陈安涛. 儿童归纳推理中的心理效应[J]. 心理科学进展,2004,12(6):835-843.  \n[7] Dweck C S. Mindset: The New Psychology of Success[M]. Random House,2006:45-67.  \n[8] 庞丽娟. 幼儿同伴互动研究的进展[J]. 心理发展与教育,1994(04):42-48.  \n[9] 教育部基础教育司. 幼儿园教育指导纲要(试行)解读[M]. 江苏教育出版社,2002:156-161.  \n[10] 陈帼眉. 学前心理学[M]. 人民教育出版社,2015:234-241.",
  "链接名称": "",
  "链接说明": "",
  "链接": "",
  "获奖等级": "",
  "获奖评语": "",
  "创建时间": "2025-03-17 16:43:53",
  "更新时间": "2025-03-25 15:08:36"
}