{
  "ID": "57812",
  "用户": "宋美娜",
  "活动": "第十四届幼儿教师优秀论文征集活动",
  "类型名称": "论文",
  "标题": "中班幼儿益智游戏中提升专注力的措施研究",
  "作者": "申婷婷，薄倩倩",
  "单位名称": "汪清县第一实验幼儿园",
  "省市": "吉林省汪清县",
  "内容": "摘要 ： 本论文围绕中班幼儿在益智游戏中提升专注力的问题展开研究。分析了幼儿在游戏过程中面临的三大挑战：注意力分散、游戏难度适应不当以及时间管理能力不足。这些问题在益智游戏的教学实践中普遍存在，影响了幼儿的专注力发展。针对这些挑战，本文提出了相应的提升策略。研究表明，合理的游戏设计与引导可以有效帮助中班幼儿提升专注力。关键词 ： 中班幼儿；益智游戏；专注力；游戏设计；时间管理正文 ：随着教育理念的更新和技术的不断进步，益智游戏在幼儿园教学中的应用逐渐增多，相关的研究和实践也得到了更多的关注。在实际应用中，仍存在许多需要深入探讨和改进的方面，特别是在如何通过益智游戏来有效提升中班幼儿的专注力方面，仍有较大的提升空间。一、提升幼儿游戏专注力的分析（一）我国幼儿益智游戏的研究现状益智游戏的设计是研究和应用的核心问题之一，研究者们更多地将精力放在如何设计出适合幼儿年龄特征、认知发展水平和兴趣点的游戏上。如何通过益智游戏中的任务难度设置、情节安排等要素，来吸引幼儿的注意力并保持其长时间的参与是设计过程中的重点。针对中班幼儿的游戏设计，既需要考虑其年龄段特有的心理和认知发展阶段，也需兼顾到其好奇心和自我表达的需求。教育效果评估是研究益智游戏的重要维度，益智游戏能够有效促进幼儿的认知发展，尤其是在提升专注力、记忆力以及解决问题的能力等方面具有显著效果。实际应用中，专注力提升的效果往往受多种因素影响，如幼儿个体差异、游戏内容的适应性以及教师的引导策略等。在当前的研究中，如何科学、系统地评估益智游戏的教育效果，尤其是对专注力的提升效果，依然是一个需要深入探索的领域。许多研究尚未完全解决如何衡量幼儿在游戏中的专注力变化，以及如何调整游戏内容和教育方法以适应不同幼儿的需求。（二）提升幼儿专注力的方法概述技术的应用成为了近年来益智游戏研究中的新兴领域。随着智能设备和互动技术的发展，越来越多的教育者和研究者开始尝试通过电子化、互动化的方式来增强益智游戏的教育功能。通过优化游戏环境、设计富有挑战性且有趣的游戏内容，以及在游戏过程中给予适当的引导和支持，都能够有效帮助中班幼儿提升专注力。现有的研究已证明，安静、有序的环境有助于减少干扰，帮助幼儿在游戏中集中注意力。教师在游戏中的引导和支持也至关重要，通过帮助幼儿理解游戏规则、制定合理的目标，能够增强他们的自主参与感和持续关注度。实践中如何精准把握这些策略的应用力度和时机，仍然需要更多的经验积累和研究支持。二、提升中班幼儿在益智游戏中专注力的问题与挑战（一）注意力分散幼儿大脑发育与专注力的关系。中班幼儿的大脑尚处于高速发展阶段，其前额叶皮层尚未完全发育成熟，这使得他们的注意力控制能力有限。当他们在游戏中面临较多选择时，容易无法集中于单一任务，而被其他更具吸引力的事物所干扰。这也是为什么在某些复杂或互动性强的游戏中，幼儿可能会频繁地转换注意力，无法长时间专注于一个任务。环境中的干扰因素。幼儿在玩游戏时，周围的声音、光线变化或者同伴的干扰都会影响其注意力的维持。许多益智游戏设计中，往往包含丰富的视觉和听觉刺激，这些多重感官的输入虽然能够提升游戏的趣味性，但对于注意力尚不稳定的中班幼儿来说，却可能成为他们分心的主要来源。色彩鲜艳的背景或过多的互动按钮可能吸引幼儿频繁点击，导致他们难以在主要任务上保持专注。如何在设计上简化不必要的刺激，通过结构化的游戏规则来引导幼儿将注意力集中在主要任务上。（二）游戏难度适应如果游戏设计的难度水平不能恰当地匹配幼儿的认知能力，往往会产生两种极端现象：过于简单导致无聊，过于复杂导致挫败。过于简单的游戏设计。当游戏的任务过于简单时，幼儿可能会在短时间内完成任务，并感到乏味或失去兴趣。在这种情况下，他们的注意力不会集中，因为游戏的挑战性不足以维持他们的思维活跃度。如果一个拼图游戏的难度太低，幼儿可能会在短时间内完成拼图并寻找其他的娱乐方式，如离开游戏区域或与其他小朋友互动。这种情况下，游戏虽然短期内吸引了幼儿的注意力，但却无法持续激发他们的专注力。过于复杂的游戏设计。相反，如果益智游戏的难度过高，幼儿可能会感到挫败和沮丧，最终选择放弃任务。中班幼儿的认知水平还处于发展阶段，他们需要逐步接受适应性挑战，才能在不断解决问题的过程中提升专注力和耐心。（三）时间管理幼儿在游戏过程中往往难以合理掌控时间，容易陷入两种极端：过度投入或过早放弃。过度投入的问题。对于一些充满趣味性和互动性的益智游戏，幼儿有时会沉迷其中，无法自我控制游戏时间。这种过度投入虽然短期内表现为高专注力，但长时间过度参与游戏会导致疲劳和注意力的下降。过早放弃的问题。相反，许多幼儿在面对较长或较为复杂的益智游戏时，往往会在短时间内感到厌倦或失去兴趣。超过50%的幼儿在益智游戏中会在10分钟内感到厌倦，选择退出游戏或转移注意力。这种现象部分源于幼儿的耐心不足，尤其是当他们在游戏中遇到挫折时，容易因为缺乏即时奖励而放弃。设计能够逐步反馈幼儿成就的游戏机制，如通过分阶段的奖励或即时正向反馈，能够在一定程度上缓解他们的放弃倾向。三、应对教学问题的提升策略（一）设置明确目标与奖励机制中班幼儿的注意力容易分散是因为他们的认知能力和情感控制尚未完全发展，在游戏过程中可能会受到外界多种刺激的干扰。为了减少分心现象，教师为每个益智游戏设置明确的目标。这些目标应该简洁且具象化，易于幼儿理解和执行。适当的奖励机制能够有效激励幼儿保持专注。分段奖励比单一的大奖励更能提高幼儿的注意力和持续投入度。教师可以在游戏中设置一些小任务，并在每个任务完成后提供小奖励。完成一次任务后，幼儿可以获得一个小贴纸、口头表扬或者短暂的游戏休息。这种即时反馈能够增强幼儿的成就感，通过小而频繁的奖励，持续刺激幼儿的专注力。奖励机制可以与游戏目标紧密结合，通过引导幼儿在完成特定目标后获得小奖励，不仅可以保持他们的兴趣，还能够有效减少分心行为。（二）调整游戏难度与个性化教学为了确保益智游戏的难度适应每个幼儿的认知能力，教师需要对幼儿的个人水平进行评估。中班幼儿由于个体差异，认知水平、问题解决能力以及专注力发展各不相同。教师在游戏设计和实施前，应该通过观察和测试了解幼儿的当前能力水平，以便针对不同的幼儿调整游戏的难度。游戏难度应以渐进式增加的方式进行，确保幼儿始终保持一定的挑战感，而不过度感到压力和挫败。教师可以通过将游戏分为多个难度层次来引导幼儿逐步完成每一层挑战。在搭建积木的游戏中，可以从简单的2块搭建任务开始，逐步增加到5块、10块，甚至是复杂的结构搭建。每完成一个难度层级，幼儿会体验到成就感，从而提升自信心与专注力。通过这种逐步升级的方式，幼儿不仅可以在游戏中保持专注，还能够通过适度的挑战来提升认知能力和问题解决能力。（三）设定明确的时间限制与时间提醒中班幼儿的注意力集中时间相对较短，通常在15-20分钟内，教师在设计游戏活动时，应根据幼儿的年龄和专注力水平设定合理的游戏时长。适当的时间限制能够帮助幼儿有效管理时间，并维持其专注力。教师可以将游戏时间设定为10分钟，然后进行一次短暂的休息。这种“工作—休息—再工作”的模式有助于避免幼儿因为长时间集中注意力而产生的疲劳感，能够提高幼儿在游戏中的效率和表现。教师还可以在游戏过程中有意识地引导幼儿进行合理的时间分配。鼓励幼儿在游戏开始时先规划如何完成任务，可以将任务分解为几步，并为每一步分配合理的时间。这种引导不仅能帮助幼儿在游戏过程中更好地管理自己的时间，还能够锻炼他们的计划能力和任务执行能力，从而提升专注力。教师也可以在游戏后和幼儿一起回顾游戏过程，讨论他们是如何利用时间的，这一反思过程可以进一步帮助幼儿建立更好的时间感知能力。结语综上所述，通过针对中班幼儿在益智游戏中专注力问题的深入分析，提出了切实可行的提升策略，包括设置明确的游戏目标与奖励机制、合理调整游戏难度、以及强化时间管理训练等。这些策略不仅能够有效解决幼儿在游戏中常见的注意力分散、难度适应不当以及时间管理能力不足等问题，还能通过逐步引导幼儿提高专注力和自我调节能力，帮助他们更好地适应未来的学习和发展需求。在幼儿园教学实践中，教师应根据每个幼儿的特点，灵活应用这些策略，创造有利于专注力培养的游戏环境，为幼儿的认知发展打下坚实基础。参考文献 ： ［1］张婷婷,孙山．益智游戏促进幼儿专注力发展的策略研究[J]．齐齐哈尔高等师范专科学校学报,2024,(2):13-15.\n［2］周洁．中班幼儿益智区活动中专注力现状及特点分析的研究[J]．课堂内外：高中版,2024,(23):72-73.\n［3］许霞．建构游戏中培养幼儿专注力的策略[J]．新课程研究,2023,(14):111-113.\n［4］雷玲．基于安吉游戏提升幼儿语言,心智和执行力研究[J]．今天,2023,(20):210-211.\n［5］蔡婷娴．区域游戏中幼儿专注力的培养策略研究[J]．教师,2023,(32):78-80.\n［6］王鹤群．幼儿结构游戏中专注力表现的特点分析研究[C]//面向可持续发展的教育研究专题研讨会（2020）.2020.\n［7］张晓慧．在游戏中培养幼儿专注力的策略分析[J]．儿童绘本,2022,(32):51-53.\n［8］梁晋彤．运用七巧板游戏培养5-6岁幼儿专注力的个案研究[D]．淮北师范大学,2021.",
  "链接名称": "",
  "链接说明": "",
  "链接": "",
  "获奖等级": "一等奖",
  "获奖评语": "",
  "创建时间": "2025-03-18 12:48:10",
  "更新时间": "2025-03-25 21:08:27"
}